openapiiplocation/__init__.py
openapiiplocation/api_client.py
openapiiplocation/api_response.py
openapiiplocation/configuration.py
openapiiplocation/exceptions.py
openapiiplocation/py.typed
openapiiplocation/rest.py
openapiiplocation/api/__init__.py
openapiiplocation/api/default_api.py
openapiiplocation/models/__init__.py
openapiiplocation/models/get200_response.py
openapiiplocation/models/get400_response.py
openapiiplocation-1.2.0.dist-info/METADATA
openapiiplocation-1.2.0.dist-info/WHEEL
openapiiplocation-1.2.0.dist-info/top_level.txt
openapiiplocation-1.2.0.dist-info/RECORD
